bader_nasser_calculator/__init__.py
bader_nasser_calculator/calculator.py
bader_nasser_calculator-0.1.0.dist-info/licenses/LICENSE
bader_nasser_calculator-0.1.0.dist-info/METADATA
bader_nasser_calculator-0.1.0.dist-info/WHEEL
bader_nasser_calculator-0.1.0.dist-info/top_level.txt
bader_nasser_calculator-0.1.0.dist-info/RECORD
