Metadata-Version: 2.4
Name: bader-nasser-calculator
Version: 0.1.0
Summary: A simple calculator package for basic math operations by Bader Nasser
Home-page: https://github.com/bader-nasser/simple-calculator
Author: بدر ناصر
Author-email: bader.nasser@example.com
Classifier: Programming Language :: Python :: 3
Classifier: License :: OSI Approved :: MIT License
Classifier: Operating System :: OS Independent
Requires-Python: >=3.6
License-File: LICENSE
Dynamic: author
Dynamic: author-email
Dynamic: classifier
Dynamic: description
Dynamic: description-content-type
Dynamic: home-page
Dynamic: license-file
Dynamic: requires-python
Dynamic: summary
